alibabacloud_yundun_bastionhost20191209/__init__.py
alibabacloud_yundun_bastionhost20191209/client.py
alibabacloud_yundun_bastionhost20191209/models/__init__.py
alibabacloud_yundun_bastionhost20191209/models/_accept_approve_command_request.py
alibabacloud_yundun_bastionhost20191209/models/_accept_approve_command_response.py
alibabacloud_yundun_bastionhost20191209/models/_accept_approve_command_response_body.py
alibabacloud_yundun_bastionhost20191209/models/_accept_operation_ticket_request.py
alibabacloud_yundun_bastionhost20191209/models/_accept_operation_ticket_response.py
alibabacloud_yundun_bastionhost20191209/models/_accept_operation_ticket_response_body.py
alibabacloud_yundun_bastionhost20191209/models/_add_databases_to_group_request.py
alibabacloud_yundun_bastionhost20191209/models/_add_databases_to_group_response.py
alibabacloud_yundun_bastionhost20191209/models/_add_databases_to_group_response_body.py
alibabacloud_yundun_bastionhost20191209/models/_add_hosts_to_group_request.py
alibabacloud_yundun_bastionhost20191209/models/_add_hosts_to_group_response.py
alibabacloud_yundun_bastionhost20191209/models/_add_hosts_to_group_response_body.py
alibabacloud_yundun_bastionhost20191209/models/_add_instance_rd_member_request.py
alibabacloud_yundun_bastionhost20191209/models/_add_instance_rd_member_response.py
alibabacloud_yundun_bastionhost20191209/models/_add_instance_rd_member_response_body.py
alibabacloud_yundun_bastionhost20191209/models/_add_users_to_group_request.py
alibabacloud_yundun_bastionhost20191209/models/_add_users_to_group_response.py
alibabacloud_yundun_bastionhost20191209/models/_add_users_to_group_response_body.py
alibabacloud_yundun_bastionhost20191209/models/_attach_database_accounts_to_user_group_request.py
alibabacloud_yundun_bastionhost20191209/models/_attach_database_accounts_to_user_group_response.py
alibabacloud_yundun_bastionhost20191209/models/_attach_database_accounts_to_user_group_response_body.py
alibabacloud_yundun_bastionhost20191209-1.4.2.dist-info/LICENSE
alibabacloud_yundun_bastionhost20191209-1.4.2.dist-info/METADATA
alibabacloud_yundun_bastionhost20191209-1.4.2.dist-info/WHEEL
alibabacloud_yundun_bastionhost20191209-1.4.2.dist-info/top_level.txt
alibabacloud_yundun_bastionhost20191209-1.4.2.dist-info/RECORD
